procsim/__init__.py
procsim/properties.py
procsim/simulator.py
procsim-1.0.1.dist-info/LICENSE.txt
procsim-1.0.1.dist-info/METADATA
procsim-1.0.1.dist-info/WHEEL
procsim-1.0.1.dist-info/top_level.txt
procsim-1.0.1.dist-info/RECORD
