Metadata-Version: 2.1
Name: procsim
Version: 1.0.1
Summary: This is a BPMN Diagram process simulator
Home-page: https://github.com/ansacaa/prosecco
Author: Antonio Sanchez Cabrera
Author-email: dev.ansaca@gmail.com
License: UNKNOWN
Keywords: BPMN,PROCESS MINING,SIMULATOR
Platform: UNKNOWN
Classifier: Development Status :: 3 - Alpha
Classifier: Intended Audience :: Developers
Classifier: Topic :: Software Development :: Build Tools
Classifier: License :: OSI Approved :: MIT License
Classifier: Programming Language :: Python :: 3
Classifier: Programming Language :: Python :: 3.4
Classifier: Programming Language :: Python :: 3.5
Classifier: Programming Language :: Python :: 3.6
Requires-Python: >=3.6
Requires-Dist: pm4pybpmn
Requires-Dist: simpy
Requires-Dist: faker
